bpoptimizer/__init__.py
bpoptimizer/cli.py
bpoptimizer/floor.py
bpoptimizer-2.0.1.dist-info/AUTHORS.rst
bpoptimizer-2.0.1.dist-info/LICENSE
bpoptimizer-2.0.1.dist-info/METADATA
bpoptimizer-2.0.1.dist-info/WHEEL
bpoptimizer-2.0.1.dist-info/entry_points.txt
bpoptimizer-2.0.1.dist-info/top_level.txt
bpoptimizer-2.0.1.dist-info/RECORD
