Metadata-Version: 2.1
Name: bpoptimizer
Version: 2.0.1
Summary: This package allows for reading a BlockParty floor as a 48x48 pixel image and provides analytics including optimized standing positions.
Home-page: https://github.com/RadioactiveDroid/bpoptimizer
Author: RadioactiveDroid
Author-email: radioactivedroid@gmail.com
License: MIT license
Keywords: bpoptimizer
Platform: UNKNOWN
Classifier: Development Status :: 2 - Pre-Alpha
Classifier: Intended Audience :: Developers
Classifier: License :: OSI Approved :: MIT License
Classifier: Natural Language :: English
Classifier: Programming Language :: Python :: 3
Classifier: Programming Language :: Python :: 3.7
Requires-Python: >=3.7
License-File: LICENSE
License-File: AUTHORS.rst
Requires-Dist: Click (>=7.0)
Requires-Dist: numpy (>=1.18)
Requires-Dist: opencv-python (>=4.1.2)
Requires-Dist: scipy (>=1.6.0)
Requires-Dist: tqdm (>=4.45.0)
